ogusa/__init__.py
ogusa/bequest_transmission.py
ogusa/calibrate.py
ogusa/calibrate_chi_n.py
ogusa/constants.py
ogusa/deterministic_profiles.py
ogusa/estimate_beta_j.py
ogusa/get_micro_data.py
ogusa/growfactor_update.py
ogusa/income.py
ogusa/labor.py
ogusa/macro_params.py
ogusa/ogusa_default_parameters.json
ogusa/psid_data_setup.py
ogusa/psid_lifetime_income.csv.gz
ogusa/psid_summ_stats.py
ogusa/transfer_distribution.py
ogusa/utils.py
ogusa/wealth.py
ogusa/wealthinit.py
ogusa-0.3.1.dist-info/licenses/LICENSE
ogusa-0.3.1.dist-info/METADATA
ogusa-0.3.1.dist-info/WHEEL
ogusa-0.3.1.dist-info/top_level.txt
ogusa-0.3.1.dist-info/RECORD
