Metadata-Version: 2.4
Name: ogusa
Version: 0.3.1
Summary: USA calibration for OG-Core
Home-page: https://github.com/PSLmodels/OG-USA/
Download-URL: https://github.com/PSLmodels/OG-USA/
Author: Jason DeBacker and Richard W. Evans
License: CC0 1.0 Universal (CC0 1.0) Public Domain Dedication
Project-URL: Issue Tracker, https://github.com/PSLmodels/OG-USA/issues
Keywords: USA calibration of large scale overlapping generations model of fiscal policy
Classifier: Development Status :: 5 - Production/Stable
Classifier: Intended Audience :: Developers
Classifier: Natural Language :: English
Classifier: License :: OSI Approved :: Common Public License
Classifier: Operating System :: POSIX
Classifier: Programming Language :: Python
Classifier: Programming Language :: Python :: 3.12
Classifier: Programming Language :: Python :: 3.13
Classifier: Topic :: Scientific/Engineering :: Information Analysis
Classifier: Topic :: Software Development :: Libraries :: Python Modules
Requires-Python: >=3.12.0, <3.14
License-File: LICENSE
Requires-Dist: numpy
Requires-Dist: psutil
Requires-Dist: scipy>=1.5.0
Requires-Dist: pandas>=1.2.5
Requires-Dist: matplotlib
Requires-Dist: dask>=2.30.0
Requires-Dist: distributed>=2.30.1
Requires-Dist: paramtools>=0.20.0
Requires-Dist: taxcalc>=4.6.0
Requires-Dist: requests
Requires-Dist: pandas-datareader
Requires-Dist: xlwt
Requires-Dist: openpyxl>=3.1.2
Requires-Dist: statsmodels
Requires-Dist: linearmodels
Requires-Dist: wheel
Requires-Dist: ogcore>=0.14.6
Dynamic: author
Dynamic: classifier
Dynamic: description
Dynamic: description-content-type
Dynamic: download-url
Dynamic: home-page
Dynamic: keywords
Dynamic: license
Dynamic: license-file
Dynamic: project-url
Dynamic: requires-dist
Dynamic: requires-python
Dynamic: summary
